src/__init__.py
src/main.py
says_hello-0.0.15.dist-info/LICENSE
says_hello-0.0.15.dist-info/METADATA
says_hello-0.0.15.dist-info/WHEEL
says_hello-0.0.15.dist-info/top_level.txt
says_hello-0.0.15.dist-info/RECORD
