Metadata-Version: 2.1
Name: says-hello
Version: 0.0.15
Summary: Returns 'Hello world'
Home-page: UNKNOWN
Author: Me
Author-email: UNKNOWN
License: UNKNOWN
Keywords: hello,python,say
Platform: UNKNOWN
Classifier: Development Status :: 1 - Planning
Classifier: Programming Language :: Python :: 3
Classifier: Operating System :: Unix
Classifier: Operating System :: MacOS :: MacOS X
Classifier: Operating System :: Microsoft :: Windows
